MANIFEST.in
README.md
build.py
requirements-dev.txt
requirements.txt
setup.py
spinneroo/__init__.py
spinneroo/elements.py
spinneroo/progress.py
spinneroo.egg-info/PKG-INFO
spinneroo.egg-info/SOURCES.txt
spinneroo.egg-info/dependency_links.txt
spinneroo.egg-info/requires.txt
spinneroo.egg-info/top_level.txt